timehelper/__init__.py
timehelper/methods.py
basic_timehelper-0.2.0.dist-info/METADATA
basic_timehelper-0.2.0.dist-info/WHEEL
basic_timehelper-0.2.0.dist-info/top_level.txt
basic_timehelper-0.2.0.dist-info/RECORD
