Metadata-Version: 2.1
Name: basic-timehelper
Version: 0.2.0
Summary: Collection of convenient methods to deal with time-related flow
Home-page: https://github.com/timehelper
Author: Paolo Gervasoni Vila
Author-email: pgervila@gmail.com
License: MIT
Platform: UNKNOWN
Classifier: License :: OSI Approved :: MIT License
Classifier: Programming Language :: Python :: 3
Classifier: Programming Language :: Python :: 3.8
Requires-Dist: pytz
Requires-Dist: pandas
